{
"type": "FeatureCollection",
"name": "Art_Galleries",
"crs": { "type": "name", "properties": { "name": "urn:ogc:def:crs:OGC:1.3:CRS84" } },
"features": [
{ "type": "Feature", "properties": { "OBJECTID": 1, "COMMON_NAME": "Aigantighe Art Gallery", "SHORT_NAME": "Aigantighe Art Gallery", "FACILITY_TYPE": "Art Gallery", "STREET_ADDRESS": "47 Wai-iti Road, Timaru", "DESCRIPTION": "Art Gallery", "LINK": "http://www.timaru.govt.nz/art-gallery.html", "ID": "6", "SOURCE": "Timaru District Council", "DATE_CREATED": "2012-02-22T00:00:00Z", "DATE_LAST_MODIFIED": "2013-03-01T00:00:00Z", "DATE_SUPPLIED": "2013-03-01T00:00:00Z", "FEATURE_ACCURACY": "+/- 10m (1:10,000)", "Feedback": "http://canterburymaps.govt.nz/Portal/Feedback/ReportLayerItem?id=6&source=064&layer=Art_Gallery" }, "geometry": { "type": "Point", "coordinates": [ 171.239685470017093, -44.390591517155244 ] } },
{ "type": "Feature", "properties": { "OBJECTID": 2, "COMMON_NAME": "Forrester Gallery", "SHORT_NAME": "Forrester Gallery", "FACILITY_TYPE": "Art Gallery", "STREET_ADDRESS": "9 Thames Street, Oamaru", "DESCRIPTION": " ", "LINK": "http://www.forrestergallery.com/", "ID": "Forrester Gallery", "SOURCE": "Waitaki District Council", "DATE_CREATED": null, "DATE_LAST_MODIFIED": null, "DATE_SUPPLIED": "2013-03-18T00:00:00Z", "FEATURE_ACCURACY": "+/- 10m (1:10,000)", "Feedback": "http://canterburymaps.govt.nz/Portal/Feedback/ReportLayerItem?id=Forrester%20Gallery&source=068&layer=Art_Gallery" }, "geometry": { "type": "Point", "coordinates": [ 170.969365050617654, -45.101483103477442 ] } },
{ "type": "Feature", "properties": { "OBJECTID": 3, "COMMON_NAME": "Waimate Art Society", "SHORT_NAME": "Art Gallery", "FACILITY_TYPE": "Art Gallery", "STREET_ADDRESS": "18 Shearman Street", "DESCRIPTION": "Waimate Art Society", "LINK": " ", "ID": " ", "SOURCE": "Waimate District Council", "DATE_CREATED": "2015-08-11T00:00:00Z", "DATE_LAST_MODIFIED": null, "DATE_SUPPLIED": "2015-10-09T00:00:00Z", "FEATURE_ACCURACY": "+/- 10m (1:10,000)", "Feedback": "http://canterburymaps.govt.nz/Portal/Feedback/ReportLayerItem?id=%20&source=066&layer=Art_Gallery" }, "geometry": { "type": "Point", "coordinates": [ 171.046980820499016, -44.731694993920378 ] } },
{ "type": "Feature", "properties": { "OBJECTID": 10, "COMMON_NAME": "Hanmer Springs Art Gallery", "SHORT_NAME": null, "FACILITY_TYPE": "Art Gallery", "STREET_ADDRESS": "49 Amuri Avenue", "DESCRIPTION": "A dedicated space in the library", "LINK": null, "ID": "CF43", "SOURCE": "Hurunui District Council", "DATE_CREATED": "2019-08-09T04:10:08Z", "DATE_LAST_MODIFIED": "2019-08-09T04:10:08Z", "DATE_SUPPLIED": "2019-09-25T00:00:00Z", "FEATURE_ACCURACY": null, "Feedback": null }, "geometry": { "type": "Point", "coordinates": [ 172.83055829509604, -42.522065952073596 ] } }
]
}
